active/__init__.py
active/active.py
active/agent/ACTIVEBootstrapAgent/bootstrap/__init__.py
active/agent/ACTIVEBootstrapAgent/bootstrap/agent.py
active/agent/ACTIVEBootstrapAgent/bootstrap/settings.py
active/agent/ACTIVEBootstrapAgent/setup.py
active/agent/__init__.py
active/agent/agent.py
active/agent/agent_factory.py
active/agent/decorators.py
active/agent/energyplustapi_agent.py
active/agent/intersect_agent.py
active/agent/simple_agent.py
active/agent/volttron_agent.py
active/controller/__init__.py
active/controller/bacnet_controller.py
active/controller/bacnet_controller_base.py
active/controller/bacnet_rtu_controller.py
active/controller/bacnet_rtu_controller_base.py
active/controller/clock_controller.py
active/controller/controller_factory.py
active/controller/cr1000x_rtu_controller.py
active/controller/cr1000x_rtu_controller_base.py
active/controller/cr3000_controller.py
active/controller/cr3000_controller_base.py
active/controller/decorators.py
active/controller/delta_solar_inverter_controller.py
active/controller/delta_solar_inverter_controller_base.py
active/controller/email_controller.py
active/controller/email_controller_base.py
active/controller/energyplus_controller.py
active/controller/energyplus_controller_base.py
active/controller/energyplusapi_clock_controller.py
active/controller/energyplusapi_rtu_controller.py
active/controller/http_controller.py
active/controller/http_controller_base.py
active/controller/intersect_controller.py
active/controller/intersect_controller_base.py
active/controller/maxtech_water_heater_controller.py
active/controller/rtu_controller.py
active/controller/system_clock_controller.py
active/controller/water_heater_controller.py
active/datastore/__init__.py
active/datastore/data_store.py
active/datastore/data_store_factory.py
active/datastore/decorators.py
active/datastore/file_system_data_store.py
active/datastore/file_system_data_store_base.py
active/datastore/postgresql_data_store.py
active_framework-2.0.9.dist-info/METADATA
active_framework-2.0.9.dist-info/WHEEL
active_framework-2.0.9.dist-info/entry_points.txt
active_framework-2.0.9.dist-info/licenses/LICENSE
active_framework-2.0.9.dist-info/RECORD
