Metadata-Version: 2.1
Name: active_framework
Version: 2.0.9
Summary: Automated Control Testbed for Integration Verification and Emulation
Author: Kadir Amasyali
Author-Email: Sen Huang <huangs@ornl.gov>, Yan Liu <yanliu@ornl.gov>, Massimiliano Lupo-Pasini <lupopasinim@ornl.gov>, Robert Smith <smithrw@ornl.gov>, Yeobeom Yoon <yoony@ornl.gov>, Helia Zandi <zandih@ornl.gov>
License: BSD-3-Clause
Classifier: Programming Language :: Python :: 3
Classifier: Programming Language :: Python :: 3.6
Classifier: Programming Language :: Python :: 3.7
Classifier: Programming Language :: Python :: 3.8
Classifier: Programming Language :: Python :: 3.9
Classifier: Programming Language :: Python :: 3.10
Classifier: Programming Language :: Python :: 3.11
Requires-Python: !=3.9.7,<4.0,>=3.9
Requires-Dist: BAC0==23.7.3
Requires-Dist: intersect-sdk==0.8.0
Requires-Dist: lxml==5.3.1
Requires-Dist: plotly==6.0.0
Requires-Dist: psychrolib==2.5.0
Requires-Dist: psycopg==3.2.5
Requires-Dist: psycopg-binary==3.2.5
Requires-Dist: pyenergyplus-lbnl==23.2.0
Requires-Dist: pytz==2021.1
Requires-Dist: requests==2.27.0
Requires-Dist: streamlit==1.43.1
